LICENSE
sphinx_cli_recorder/__init__.py
sphinx_cli_recorder/asciinema-player.css
sphinx_cli_recorder/asciinema-player.min.js
sphinx_cli_recorder/asciinema_block_parser.py
sphinx_cli_recorder/asciinema_player_settings.py
sphinx_cli_recorder/custom-asciinema-rules.css
sphinx_cli_recorder/scripted_asciinema_runner.py
sphinx_cli_recorder/scripted_cmds.py
sphinx_cli_recorder/testing/animation_example.py
sphinx_cli_recorder/testing/prompt.py
sphinx_cli_recorder/testing/tiny_prompt.py
sphinx_cli_recorder-0.1.6.dist-info/WHEEL
sphinx_cli_recorder-0.1.6.dist-info/METADATA
sphinx_cli_recorder-0.1.6.dist-info/license_files/LICENSE
sphinx_cli_recorder-0.1.6.dist-info/RECORD
