Metadata-Version: 2.1
Name: sphinx-cli-recorder
Version: 0.1.6
Summary: A Sphinx extension that runs/automates recordings of CLI applications, without requiring any external services.
License: GNU General Public License v3
Author-email: Kai Norman Clasen <k.clasen@protonmail.com>
Requires-Python: >=3.8, <3.12
Requires-Dist: PyYAML>=6.0
Requires-Dist: Sphinx>=4.4
Requires-Dist: asciinema>=2.2.0
Requires-Dist: asyncer>=0.0.1
Requires-Dist: pexpect>=4.8
Requires-Dist: pydantic>=1.9.0
Requires-Dist: unsync>=1.4
Requires-Dist: yamale>=4.0.3
Project-URL: documentation, https://kai-tub.github.io/sphinx_cli_recorder
Project-URL: homepage, https://github.com/kai-tub/sphinx_cli_recorder/
Project-URL: repository, https://github.com/kai-tub/sphinx_cli_recorder/
